gkdtikz/__init__.py
gkdtikz/tree/__init__.py
gkdtikz-0.1.1.dist-info/LICENSE
gkdtikz-0.1.1.dist-info/METADATA
gkdtikz-0.1.1.dist-info/WHEEL
gkdtikz-0.1.1.dist-info/entry_points.txt
gkdtikz-0.1.1.dist-info/top_level.txt
gkdtikz-0.1.1.dist-info/RECORD
