Metadata-Version: 2.1
Name: gkdtikz
Version: 0.1.1
Summary: wrapping tikz in gkdtex for simplifying the use of Tikz in a factor of 114514.
Home-page: https://github.com/thautwarm/gkdtikz
Author: thautwarm
Author-email: twshere@outlook.com
License: mit
Keywords: TeX,TikZ
Platform: any
Classifier: Programming Language :: Python :: 3.6
Classifier: Programming Language :: Python :: 3.7
Classifier: Programming Language :: Python :: 3.8
Classifier: Programming Language :: Python :: Implementation :: CPython
Requires-Python: >=3.6.0
Requires-Dist: pyyaml
Requires-Dist: gkdtex
